{
	"sentences": [
		{
			"text": {
				"content": "치안이 민영화 된 사회!",
				"beginOffset": 0
			}
		},
		{
			"text": {
				"content": "치안전문주식회사 <저스티스>는 경찰력 대신 초능력자를 고용한다.",
				"beginOffset": 32
			}
		},
		{
			"text": {
				"content": "월급 받고 도시를 지키는 초능력자들의 이야기",
				"beginOffset": 122
			}
		}
	],
	"tokens": [
		{
			"text": {
				"content": "치안",
				"beginOffset": 0
			},
			"partOfSpeech": {
				"tag": "NOUN",
				"aspect": "ASPECT_UNKNOWN",
				"case": "CASE_UNKNOWN",
				"form": "FORM_UNKNOWN",
				"gender": "GENDER_UNKNOWN",
				"mood": "MOOD_UNKNOWN",
				"number": "NUMBER_UNKNOWN",
				"person": "PERSON_UNKNOWN",
				"proper": "NOT_PROPER",
				"reciprocity": "RECIPROCITY_UNKNOWN",
				"tense": "TENSE_UNKNOWN",
				"voice": "VOICE_UNKNOWN"
			},
			"dependencyEdge": {
				"headTokenIndex": 2,
				"label": "NSUBJ"
			},
			"lemma": "치안"
		},
		{
			"text": {
				"content": "이",
				"beginOffset": 6
			},
			"partOfSpeech": {
				"tag": "PRT",
				"aspect": "ASPECT_UNKNOWN",
				"case": "NOMINATIVE",
				"form": "FORM_UNKNOWN",
				"gender": "GENDER_UNKNOWN",
				"mood": "MOOD_UNKNOWN",
				"number": "NUMBER_UNKNOWN",
				"person": "PERSON_UNKNOWN",
				"proper": "NOT_PROPER",
				"reciprocity": "RECIPROCITY_UNKNOWN",
				"tense": "TENSE_UNKNOWN",
				"voice": "VOICE_UNKNOWN"
			},
			"dependencyEdge": {
				"headTokenIndex": 0,
				"label": "PRT"
			},
			"lemma": "이"
		},
		{
			"text": {
				"content": "민영",
				"beginOffset": 10
			},
			"partOfSpeech": {
				"tag": "NOUN",
				"aspect": "ASPECT_UNKNOWN",
				"case": "CASE_UNKNOWN",
				"form": "FORM_UNKNOWN",
				"gender": "GENDER_UNKNOWN",
				"mood": "MOOD_UNKNOWN",
				"number": "NUMBER_UNKNOWN",
				"person": "PERSON_UNKNOWN",
				"proper": "NOT_PROPER",
				"reciprocity": "RECIPROCITY_UNKNOWN",
				"tense": "TENSE_UNKNOWN",
				"voice": "VOICE_UNKNOWN"
			},
			"dependencyEdge": {
				"headTokenIndex": 5,
				"label": "RCMOD"
			},
			"lemma": "민영"
		},
		{
			"text": {
				"content": "화",
				"beginOffset": 16
			},
			"partOfSpeech": {
				"tag": "AFFIX",
				"aspect": "ASPECT_UNKNOWN",
				"case": "CASE_UNKNOWN",
				"form": "FORM_UNKNOWN",
				"gender": "GENDER_UNKNOWN",
				"mood": "MOOD_UNKNOWN",
				"number": "NUMBER_UNKNOWN",
				"person": "PERSON_UNKNOWN",
				"proper": "NOT_PROPER",
				"reciprocity": "RECIPROCITY_UNKNOWN",
				"tense": "TENSE_UNKNOWN",
				"voice": "VOICE_UNKNOWN"
			},
			"dependencyEdge": {
				"headTokenIndex": 2,
				"label": "SUFF"
			},
			"lemma": "화"
		},
		{
			"text": {
				"content": "된",
				"beginOffset": 20
			},
			"partOfSpeech": {
				"tag": "AFFIX",
				"aspect": "ASPECT_UNKNOWN",
				"case": "CASE_UNKNOWN",
				"form": "ADNOMIAL",
				"gender": "GENDER_UNKNOWN",
				"mood": "MOOD_UNKNOWN",
				"number": "NUMBER_UNKNOWN",
				"person": "PERSON_UNKNOWN",
				"proper": "NOT_PROPER",
				"reciprocity": "RECIPROCITY_UNKNOWN",
				"tense": "PAST",
				"voice": "PASSIVE"
			},
			"dependencyEdge": {
				"headTokenIndex": 2,
				"label": "SUFF"
			},
			"lemma": "된"
		},
		{
			"text": {
				"content": "사회",
				"beginOffset": 24
			},
			"partOfSpeech": {
				"tag": "NOUN",
				"aspect": "ASPECT_UNKNOWN",
				"case": "CASE_UNKNOWN",
				"form": "FINAL_ENDING",
				"gender": "GENDER_UNKNOWN",
				"mood": "MOOD_UNKNOWN",
				"number": "NUMBER_UNKNOWN",
				"person": "PERSON_UNKNOWN",
				"proper": "NOT_PROPER",
				"reciprocity": "RECIPROCITY_UNKNOWN",
				"tense": "TENSE_UNKNOWN",
				"voice": "VOICE_UNKNOWN"
			},
			"dependencyEdge": {
				"headTokenIndex": 5,
				"label": "ROOT"
			},
			"lemma": "사회"
		},
		{
			"text": {
				"content": "!",
				"beginOffset": 30
			},
			"partOfSpeech": {
				"tag": "PUNCT",
				"aspect": "ASPECT_UNKNOWN",
				"case": "CASE_UNKNOWN",
				"form": "FORM_UNKNOWN",
				"gender": "GENDER_UNKNOWN",
				"mood": "MOOD_UNKNOWN",
				"number": "NUMBER_UNKNOWN",
				"person": "PERSON_UNKNOWN",
				"proper": "NOT_PROPER",
				"reciprocity": "RECIPROCITY_UNKNOWN",
				"tense": "TENSE_UNKNOWN",
				"voice": "VOICE_UNKNOWN"
			},
			"dependencyEdge": {
				"headTokenIndex": 5,
				"label": "P"
			},
			"lemma": "!"
		},
		{
			"text": {
				"content": "치안전",
				"beginOffset": 32
			},
			"partOfSpeech": {
				"tag": "NOUN",
				"aspect": "ASPECT_UNKNOWN",
				"case": "CASE_UNKNOWN",
				"form": "FORM_UNKNOWN",
				"gender": "GENDER_UNKNOWN",
				"mood": "MOOD_UNKNOWN",
				"number": "NUMBER_UNKNOWN",
				"person": "PERSON_UNKNOWN",
				"proper": "NOT_PROPER",
				"reciprocity": "RECIPROCITY_UNKNOWN",
				"tense": "TENSE_UNKNOWN",
				"voice": "VOICE_UNKNOWN"
			},
			"dependencyEdge": {
				"headTokenIndex": 8,
				"label": "NN"
			},
			"lemma": "치안전"
		},
		{
			"text": {
				"content": "문",
				"beginOffset": 41
			},
			"partOfSpeech": {
				"tag": "NOUN",
				"aspect": "ASPECT_UNKNOWN",
				"case": "CASE_UNKNOWN",
				"form": "FORM_UNKNOWN",
				"gender": "GENDER_UNKNOWN",
				"mood": "MOOD_UNKNOWN",
				"number": "NUMBER_UNKNOWN",
				"person": "PERSON_UNKNOWN",
				"proper": "NOT_PROPER",
				"reciprocity": "RECIPROCITY_UNKNOWN",
				"tense": "TENSE_UNKNOWN",
				"voice": "VOICE_UNKNOWN"
			},
			"dependencyEdge": {
				"headTokenIndex": 9,
				"label": "NN"
			},
			"lemma": "문"
		},
		{
			"text": {
				"content": "주식",
				"beginOffset": 44
			},
			"partOfSpeech": {
				"tag": "NOUN",
				"aspect": "ASPECT_UNKNOWN",
				"case": "CASE_UNKNOWN",
				"form": "FORM_UNKNOWN",
				"gender": "GENDER_UNKNOWN",
				"mood": "MOOD_UNKNOWN",
				"number": "NUMBER_UNKNOWN",
				"person": "PERSON_UNKNOWN",
				"proper": "NOT_PROPER",
				"reciprocity": "RECIPROCITY_UNKNOWN",
				"tense": "TENSE_UNKNOWN",
				"voice": "VOICE_UNKNOWN"
			},
			"dependencyEdge": {
				"headTokenIndex": 10,
				"label": "NN"
			},
			"lemma": "주식"
		},
		{
			"text": {
				"content": "회사",
				"beginOffset": 50
			},
			"partOfSpeech": {
				"tag": "NOUN",
				"aspect": "ASPECT_UNKNOWN",
				"case": "CASE_UNKNOWN",
				"form": "FORM_UNKNOWN",
				"gender": "GENDER_UNKNOWN",
				"mood": "MOOD_UNKNOWN",
				"number": "NUMBER_UNKNOWN",
				"person": "PERSON_UNKNOWN",
				"proper": "NOT_PROPER",
				"reciprocity": "RECIPROCITY_UNKNOWN",
				"tense": "TENSE_UNKNOWN",
				"voice": "VOICE_UNKNOWN"
			},
			"dependencyEdge": {
				"headTokenIndex": 11,
				"label": "NN"
			},
			"lemma": "회사"
		},
		{
			"text": {
				"content": "<",
				"beginOffset": 57
			},
			"partOfSpeech": {
				"tag": "NOUN",
				"aspect": "ASPECT_UNKNOWN",
				"case": "CASE_UNKNOWN",
				"form": "FORM_UNKNOWN",
				"gender": "GENDER_UNKNOWN",
				"mood": "MOOD_UNKNOWN",
				"number": "NUMBER_UNKNOWN",
				"person": "PERSON_UNKNOWN",
				"proper": "NOT_PROPER",
				"reciprocity": "RECIPROCITY_UNKNOWN",
				"tense": "TENSE_UNKNOWN",
				"voice": "VOICE_UNKNOWN"
			},
			"dependencyEdge": {
				"headTokenIndex": 13,
				"label": "NN"
			},
			"lemma": "<"
		},
		{
			"text": {
				"content": "저스티스",
				"beginOffset": 58
			},
			"partOfSpeech": {
				"tag": "NOUN",
				"aspect": "ASPECT_UNKNOWN",
				"case": "CASE_UNKNOWN",
				"form": "FORM_UNKNOWN",
				"gender": "GENDER_UNKNOWN",
				"mood": "MOOD_UNKNOWN",
				"number": "NUMBER_UNKNOWN",
				"person": "PERSON_UNKNOWN",
				"proper": "PROPER",
				"reciprocity": "RECIPROCITY_UNKNOWN",
				"tense": "TENSE_UNKNOWN",
				"voice": "VOICE_UNKNOWN"
			},
			"dependencyEdge": {
				"headTokenIndex": 13,
				"label": "NN"
			},
			"lemma": "저스티스"
		},
		{
			"text": {
				"content": ">",
				"beginOffset": 70
			},
			"partOfSpeech": {
				"tag": "NOUN",
				"aspect": "ASPECT_UNKNOWN",
				"case": "CASE_UNKNOWN",
				"form": "FORM_UNKNOWN",
				"gender": "GENDER_UNKNOWN",
				"mood": "MOOD_UNKNOWN",
				"number": "NUMBER_UNKNOWN",
				"person": "PERSON_UNKNOWN",
				"proper": "NOT_PROPER",
				"reciprocity": "RECIPROCITY_UNKNOWN",
				"tense": "TENSE_UNKNOWN",
				"voice": "VOICE_UNKNOWN"
			},
			"dependencyEdge": {
				"headTokenIndex": 19,
				"label": "NSUBJ"
			},
			"lemma": ">"
		},
		{
			"text": {
				"content": "는",
				"beginOffset": 71
			},
			"partOfSpeech": {
				"tag": "PRT",
				"aspect": "ASPECT_UNKNOWN",
				"case": "NOMINATIVE",
				"form": "FORM_UNKNOWN",
				"gender": "GENDER_UNKNOWN",
				"mood": "MOOD_UNKNOWN",
				"number": "NUMBER_UNKNOWN",
				"person": "PERSON_UNKNOWN",
				"proper": "NOT_PROPER",
				"reciprocity": "RECIPROCITY_UNKNOWN",
				"tense": "TENSE_UNKNOWN",
				"voice": "VOICE_UNKNOWN"
			},
			"dependencyEdge": {
				"headTokenIndex": 13,
				"label": "PRT"
			},
			"lemma": "는"
		},
		{
			"text": {
				"content": "경찰력",
				"beginOffset": 75
			},
			"partOfSpeech": {
				"tag": "NOUN",
				"aspect": "ASPECT_UNKNOWN",
				"case": "CASE_UNKNOWN",
				"form": "FORM_UNKNOWN",
				"gender": "GENDER_UNKNOWN",
				"mood": "MOOD_UNKNOWN",
				"number": "NUMBER_UNKNOWN",
				"person": "PERSON_UNKNOWN",
				"proper": "NOT_PROPER",
				"reciprocity": "RECIPROCITY_UNKNOWN",
				"tense": "TENSE_UNKNOWN",
				"voice": "VOICE_UNKNOWN"
			},
			"dependencyEdge": {
				"headTokenIndex": 16,
				"label": "NN"
			},
			"lemma": "경찰력"
		},
		{
			"text": {
				"content": "대신",
				"beginOffset": 85
			},
			"partOfSpeech": {
				"tag": "NOUN",
				"aspect": "ASPECT_UNKNOWN",
				"case": "CASE_UNKNOWN",
				"form": "FORM_UNKNOWN",
				"gender": "GENDER_UNKNOWN",
				"mood": "MOOD_UNKNOWN",
				"number": "NUMBER_UNKNOWN",
				"person": "PERSON_UNKNOWN",
				"proper": "NOT_PROPER",
				"reciprocity": "RECIPROCITY_UNKNOWN",
				"tense": "TENSE_UNKNOWN",
				"voice": "VOICE_UNKNOWN"
			},
			"dependencyEdge": {
				"headTokenIndex": 19,
				"label": "ADVMOD"
			},
			"lemma": "대신"
		},
		{
			"text": {
				"content": "초능력자",
				"beginOffset": 92
			},
			"partOfSpeech": {
				"tag": "NOUN",
				"aspect": "ASPECT_UNKNOWN",
				"case": "CASE_UNKNOWN",
				"form": "FORM_UNKNOWN",
				"gender": "GENDER_UNKNOWN",
				"mood": "MOOD_UNKNOWN",
				"number": "NUMBER_UNKNOWN",
				"person": "PERSON_UNKNOWN",
				"proper": "NOT_PROPER",
				"reciprocity": "RECIPROCITY_UNKNOWN",
				"tense": "TENSE_UNKNOWN",
				"voice": "VOICE_UNKNOWN"
			},
			"dependencyEdge": {
				"headTokenIndex": 19,
				"label": "DOBJ"
			},
			"lemma": "초능력자"
		},
		{
			"text": {
				"content": "를",
				"beginOffset": 104
			},
			"partOfSpeech": {
				"tag": "PRT",
				"aspect": "ASPECT_UNKNOWN",
				"case": "ACCUSATIVE",
				"form": "FORM_UNKNOWN",
				"gender": "GENDER_UNKNOWN",
				"mood": "MOOD_UNKNOWN",
				"number": "NUMBER_UNKNOWN",
				"person": "PERSON_UNKNOWN",
				"proper": "NOT_PROPER",
				"reciprocity": "RECIPROCITY_UNKNOWN",
				"tense": "TENSE_UNKNOWN",
				"voice": "VOICE_UNKNOWN"
			},
			"dependencyEdge": {
				"headTokenIndex": 17,
				"label": "PRT"
			},
			"lemma": "를"
		},
		{
			"text": {
				"content": "고용",
				"beginOffset": 108
			},
			"partOfSpeech": {
				"tag": "NOUN",
				"aspect": "ASPECT_UNKNOWN",
				"case": "CASE_UNKNOWN",
				"form": "FORM_UNKNOWN",
				"gender": "GENDER_UNKNOWN",
				"mood": "MOOD_UNKNOWN",
				"number": "NUMBER_UNKNOWN",
				"person": "PERSON_UNKNOWN",
				"proper": "NOT_PROPER",
				"reciprocity": "RECIPROCITY_UNKNOWN",
				"tense": "TENSE_UNKNOWN",
				"voice": "VOICE_UNKNOWN"
			},
			"dependencyEdge": {
				"headTokenIndex": 19,
				"label": "ROOT"
			},
			"lemma": "고용"
		},
		{
			"text": {
				"content": "한다",
				"beginOffset": 114
			},
			"partOfSpeech": {
				"tag": "AFFIX",
				"aspect": "ASPECT_UNKNOWN",
				"case": "CASE_UNKNOWN",
				"form": "FINAL_ENDING",
				"gender": "GENDER_UNKNOWN",
				"mood": "INDICATIVE",
				"number": "NUMBER_UNKNOWN",
				"person": "PERSON_UNKNOWN",
				"proper": "NOT_PROPER",
				"reciprocity": "RECIPROCITY_UNKNOWN",
				"tense": "TENSE_UNKNOWN",
				"voice": "VOICE_UNKNOWN"
			},
			"dependencyEdge": {
				"headTokenIndex": 19,
				"label": "SUFF"
			},
			"lemma": "한다"
		},
		{
			"text": {
				"content": ".",
				"beginOffset": 120
			},
			"partOfSpeech": {
				"tag": "PUNCT",
				"aspect": "ASPECT_UNKNOWN",
				"case": "CASE_UNKNOWN",
				"form": "FORM_UNKNOWN",
				"gender": "GENDER_UNKNOWN",
				"mood": "MOOD_UNKNOWN",
				"number": "NUMBER_UNKNOWN",
				"person": "PERSON_UNKNOWN",
				"proper": "NOT_PROPER",
				"reciprocity": "RECIPROCITY_UNKNOWN",
				"tense": "TENSE_UNKNOWN",
				"voice": "VOICE_UNKNOWN"
			},
			"dependencyEdge": {
				"headTokenIndex": 19,
				"label": "P"
			},
			"lemma": "."
		},
		{
			"text": {
				"content": "월급",
				"beginOffset": 122
			},
			"partOfSpeech": {
				"tag": "NOUN",
				"aspect": "ASPECT_UNKNOWN",
				"case": "CASE_UNKNOWN",
				"form": "FORM_UNKNOWN",
				"gender": "GENDER_UNKNOWN",
				"mood": "MOOD_UNKNOWN",
				"number": "NUMBER_UNKNOWN",
				"person": "PERSON_UNKNOWN",
				"proper": "NOT_PROPER",
				"reciprocity": "RECIPROCITY_UNKNOWN",
				"tense": "TENSE_UNKNOWN",
				"voice": "VOICE_UNKNOWN"
			},
			"dependencyEdge": {
				"headTokenIndex": 26,
				"label": "ADVCL"
			},
			"lemma": "월급"
		},
		{
			"text": {
				"content": "받고",
				"beginOffset": 129
			},
			"partOfSpeech": {
				"tag": "AFFIX",
				"aspect": "ASPECT_UNKNOWN",
				"case": "CASE_UNKNOWN",
				"form": "COMPLEMENTIZER",
				"gender": "GENDER_UNKNOWN",
				"mood": "MOOD_UNKNOWN",
				"number": "NUMBER_UNKNOWN",
				"person": "PERSON_UNKNOWN",
				"proper": "NOT_PROPER",
				"reciprocity": "RECIPROCITY_UNKNOWN",
				"tense": "TENSE_UNKNOWN",
				"voice": "VOICE_UNKNOWN"
			},
			"dependencyEdge": {
				"headTokenIndex": 22,
				"label": "SUFF"
			},
			"lemma": "받고"
		},
		{
			"text": {
				"content": "도시",
				"beginOffset": 136
			},
			"partOfSpeech": {
				"tag": "NOUN",
				"aspect": "ASPECT_UNKNOWN",
				"case": "CASE_UNKNOWN",
				"form": "FORM_UNKNOWN",
				"gender": "GENDER_UNKNOWN",
				"mood": "MOOD_UNKNOWN",
				"number": "NUMBER_UNKNOWN",
				"person": "PERSON_UNKNOWN",
				"proper": "NOT_PROPER",
				"reciprocity": "RECIPROCITY_UNKNOWN",
				"tense": "TENSE_UNKNOWN",
				"voice": "VOICE_UNKNOWN"
			},
			"dependencyEdge": {
				"headTokenIndex": 26,
				"label": "DOBJ"
			},
			"lemma": "도시"
		},
		{
			"text": {
				"content": "를",
				"beginOffset": 142
			},
			"partOfSpeech": {
				"tag": "PRT",
				"aspect": "ASPECT_UNKNOWN",
				"case": "ACCUSATIVE",
				"form": "FORM_UNKNOWN",
				"gender": "GENDER_UNKNOWN",
				"mood": "MOOD_UNKNOWN",
				"number": "NUMBER_UNKNOWN",
				"person": "PERSON_UNKNOWN",
				"proper": "NOT_PROPER",
				"reciprocity": "RECIPROCITY_UNKNOWN",
				"tense": "TENSE_UNKNOWN",
				"voice": "VOICE_UNKNOWN"
			},
			"dependencyEdge": {
				"headTokenIndex": 24,
				"label": "PRT"
			},
			"lemma": "를"
		},
		{
			"text": {
				"content": "지키는",
				"beginOffset": 146
			},
			"partOfSpeech": {
				"tag": "VERB",
				"aspect": "ASPECT_UNKNOWN",
				"case": "CASE_UNKNOWN",
				"form": "ADNOMIAL",
				"gender": "GENDER_UNKNOWN",
				"mood": "MOOD_UNKNOWN",
				"number": "NUMBER_UNKNOWN",
				"person": "PERSON_UNKNOWN",
				"proper": "NOT_PROPER",
				"reciprocity": "RECIPROCITY_UNKNOWN",
				"tense": "TENSE_UNKNOWN",
				"voice": "VOICE_UNKNOWN"
			},
			"dependencyEdge": {
				"headTokenIndex": 29,
				"label": "RCMOD"
			},
			"lemma": "지키는"
		},
		{
			"text": {
				"content": "초능력자들",
				"beginOffset": 156
			},
			"partOfSpeech": {
				"tag": "NOUN",
				"aspect": "ASPECT_UNKNOWN",
				"case": "CASE_UNKNOWN",
				"form": "FORM_UNKNOWN",
				"gender": "GENDER_UNKNOWN",
				"mood": "MOOD_UNKNOWN",
				"number": "NUMBER_UNKNOWN",
				"person": "PERSON_UNKNOWN",
				"proper": "NOT_PROPER",
				"reciprocity": "RECIPROCITY_UNKNOWN",
				"tense": "TENSE_UNKNOWN",
				"voice": "VOICE_UNKNOWN"
			},
			"dependencyEdge": {
				"headTokenIndex": 29,
				"label": "POSS"
			},
			"lemma": "초능력자들"
		},
		{
			"text": {
				"content": "의",
				"beginOffset": 171
			},
			"partOfSpeech": {
				"tag": "PRT",
				"aspect": "ASPECT_UNKNOWN",
				"case": "GENITIVE",
				"form": "FORM_UNKNOWN",
				"gender": "GENDER_UNKNOWN",
				"mood": "MOOD_UNKNOWN",
				"number": "NUMBER_UNKNOWN",
				"person": "PERSON_UNKNOWN",
				"proper": "NOT_PROPER",
				"reciprocity": "RECIPROCITY_UNKNOWN",
				"tense": "TENSE_UNKNOWN",
				"voice": "VOICE_UNKNOWN"
			},
			"dependencyEdge": {
				"headTokenIndex": 27,
				"label": "PRT"
			},
			"lemma": "의"
		},
		{
			"text": {
				"content": "이야기",
				"beginOffset": 175
			},
			"partOfSpeech": {
				"tag": "NOUN",
				"aspect": "ASPECT_UNKNOWN",
				"case": "CASE_UNKNOWN",
				"form": "FORM_UNKNOWN",
				"gender": "GENDER_UNKNOWN",
				"mood": "MOOD_UNKNOWN",
				"number": "NUMBER_UNKNOWN",
				"person": "PERSON_UNKNOWN",
				"proper": "NOT_PROPER",
				"reciprocity": "RECIPROCITY_UNKNOWN",
				"tense": "TENSE_UNKNOWN",
				"voice": "VOICE_UNKNOWN"
			},
			"dependencyEdge": {
				"headTokenIndex": 29,
				"label": "ROOT"
			},
			"lemma": "이야기"
		}
	],
	"language": "ko"
}